dron/__main__.py
dron/api.py
dron/cli.py
dron/common.py
dron/conftest.py
dron/dron.py
dron/launchd.py
dron/launchd_wrapper.py
dron/monitor.py
dron/py.typed
dron/systemd.py
dron/notify/common.py
dron/notify/email.py
dron/notify/ntfy_common.py
dron/notify/ntfy_desktop.py
dron/notify/ntfy_telegram.py
dron/notify/telegram.py
dron/tests/test_dron.py
dron-0.2.20251011.dist-info/METADATA
dron-0.2.20251011.dist-info/WHEEL
dron-0.2.20251011.dist-info/entry_points.txt
dron-0.2.20251011.dist-info/licenses/LICENSE.txt
dron-0.2.20251011.dist-info/RECORD
