Metadata-Version: 2.4
Name: dron
Version: 0.2.20251011
Summary: What if cron and systemd had a baby?
Project-URL: Homepage, https://github.com/karlicoss/dron
Author-email: "Dima Gerasimov (@karlicoss)" <karlicoss@gmail.com>
Maintainer-email: "Dima Gerasimov (@karlicoss)" <karlicoss@gmail.com>
License: The MIT License (MIT)
License-File: LICENSE.txt
Requires-Python: >=3.12
Requires-Dist: click
Requires-Dist: dbus-python; platform_system != 'Darwin'
Requires-Dist: loguru
Requires-Dist: mypy
Requires-Dist: prompt-toolkit
Requires-Dist: tabulate
Requires-Dist: termcolor
Requires-Dist: textual
Requires-Dist: tzlocal
Provides-Extra: notify-telegram
Requires-Dist: telegram-send>=0.37; extra == 'notify-telegram'
